MANIFEST.in
README.txt
setup.cfg
setup.py
adi/__init__.py
adi.simplesite.egg-info/PKG-INFO
adi.simplesite.egg-info/SOURCES.txt
adi.simplesite.egg-info/dependency_links.txt
adi.simplesite.egg-info/entry_points.txt
adi.simplesite.egg-info/namespace_packages.txt
adi.simplesite.egg-info/not-zip-safe
adi.simplesite.egg-info/paster_plugins.txt
adi.simplesite.egg-info/requires.txt
adi.simplesite.egg-info/top_level.txt
adi/simplesite/__init__.py
adi/simplesite/configure.zcml
adi/simplesite/tests.py
adi/simplesite/profiles/default/metadata.xml
adi/simplesite/profiles/default/propertiestool.xml
docs/HISTORY.txt
docs/INSTALL.txt
docs/LICENSE.GPL
docs/LICENSE.txt