Metadata-Version: 1.1
Name: adi.simplesite
Version: 0.6
Summary: Configs for small sites
Home-page: http://svn.plone.org/svn/collective/adi.simplesite
Author: Ida Ebkes
Author-email: contact@ida-ebkes.eu
License: GPL
Platform: UNKNOWN
Classifier: Framework :: Plone
Classifier: Programming Language :: Python
